Pycco-0.6.0.dist-info/METADATA
Pycco-0.6.0.dist-info/RECORD
Pycco-0.6.0.dist-info/WHEEL
Pycco-0.6.0.dist-info/entry_points.txt
Pycco-0.6.0.dist-info/top_level.txt
pycco/__init__.py
pycco/compat.py
pycco/generate_index.py
pycco/languages.py
pycco/main.py
pycco_resources/__init__.py
tests/__init__.py
tests/test_pycco.py
