Metadata-Version: 2.1
Name: Pycco
Version: 0.6.0
Summary: A Python port of Docco: the original quick-and-dirty, hundred-line-long, literate-programming-style documentation generator.
Home-page: https://pycco-docs.github.io/pycco/
Author: Zach Smith
Author-email: subsetpark@gmail.com
License: UNKNOWN
Platform: UNKNOWN
Provides-Extra: monitoring
